{
  "chunk_id": "cahps__ffs-cahps-datadictionary-2025-ccw_pdf__ca6eb08dee__p37__chunk_2",
  "source_document": "data/raw/assets/pdf/ca6eb08deec69a2ca0c053e0e47dab882908b143.pdf",
  "page": 37,
  "text": "FFS \nQ35 \nx-ray, blood test, or EKG for heart conditions?\nMA-PD \nQ32 \nIn the last 6 months, did you get information or help from your health plan’s customer service? \ncs_cstryinfo \nMA-Only \nQ32 \nFFS \nQ36 \nIn the last 6 months, did you get information or help from Medicare’s customer service? \nMA-PD \nQ33 \nIn the last 6 months, how often did your health plan’s customer service give you the information or help you \ncs_csgetinfo \nMA-Only \nQ33 \nneeded?\nFFS \nQ37 \nIn the last 6 months, how often did",
  "dataset": "cahps",
  "url": "https://resdac.org/sites/datadocumentation.resdac.org/files/2026-05/FFS_CAHPS_DataDictionary_2025_CCW.pdf"
}