{
  "chunk_id": "cahps__ffs-cahps-datadictionary-2025-ccw_pdf__ca6eb08dee__p50__chunk_0",
  "source_document": "data/raw/assets/pdf/ca6eb08deec69a2ca0c053e0e47dab882908b143.pdf",
  "page": 50,
  "text": "A. Crosswalk: 2007 to 2025 - Original Medicare Survey \n50 \nVariable \nReverse \n2016 \n2015 \n2014 \n2013 \n2012 \n2011 \n2010 \n2009 \n2008 \nYear 10 \nYear 9 \nYear 8 \nYear 7 \nYear 6 \nYear 5 \nYear 4 \nYear 3 \nYear 2 \nma_nocare \nQ54 \nQ54 \nQ54 \nQ49 \nQ46 \nQ36 \n—– \n—– \n—– \nma_reconsid \nQ55 \nQ55 \nQ55 \nQ50 \nQ47 \nQ37 \n—– \n—– \n—– \nma_appeal \nQ56A \nQ56A \nQ56A \nQ51A \nQ48A \nQ38A \n—– \n—– \n—– \nma_forms \nQ56B \nQ56B \nQ56B \nQ51B \nQ48B \nQ38B \n—– \n—– \n—– \nma_resolve \nQ56C \nQ56C \nQ56C \nQ51C \nQ48C \nQ38C \n—– \n—– \n—– \nma_listen",
  "dataset": "cahps",
  "url": "https://resdac.org/sites/datadocumentation.resdac.org/files/2026-05/FFS_CAHPS_DataDictionary_2025_CCW.pdf"
}