{
  "chunk_id": "cahps__ffs-cahps-datadictionary-2025-ccw_pdf__ca6eb08dee__p46__chunk_4",
  "source_document": "data/raw/assets/pdf/ca6eb08deec69a2ca0c053e0e47dab882908b143.pdf",
  "page": 46,
  "text": "Q51E \nQ56E \nQ56E \nQ56E \nQ56E \nQ56E \nQ56E \nQ56E \ncnd_diabetes \nQ50F \nQ51F \nQ56F \nQ56F \nQ56F \nQ56F \nQ56F \nQ56F \nQ56F \nprob_walking \n—– \n—– \n—– \n—– \n—– \n—– \n—– \n—– \n—– \nprob_dressing \n—– \n—– \n—– \n—– \n—– \n—– \n—– \n—– \n—– \nprob_errands \nQ58 \nQ64 \nQ66 \nQ66 \nQ66 \nQ66 \nQ66 \nQ66 \nQ66 \nim_flu1last* \nR \nQ51 \nQ52 \nQ57 \nQ57 \nQ57 \nQ57 \nQ57 \nQ57 \nQ57 \nim_flu1plan \nim_pneum* \nR \nQ52 \nQ53 \nQ58 \nQ58 \nQ58 \nQ58 \nQ58 \nQ58 \nQ58 \nsmokenow \nD \nQ54 \nQ59 \nQ59 \nQ59 \nQ59 \nQ59 \nQ59 \nQ59",
  "dataset": "cahps",
  "url": "https://resdac.org/sites/datadocumentation.resdac.org/files/2026-05/FFS_CAHPS_DataDictionary_2025_CCW.pdf"
}