{
  "chunk_id": "cahps__ma-pdp-cahps-datadictionary-2025-ccw_pdf__d2602cbe44__p47__chunk_0",
  "source_document": "data/raw/assets/pdf/d2602cbe44c673c77cf8472b3ff5f084d5a5c3aa.pdf",
  "page": 47,
  "text": "A. Crosswalk: 2007 to 2025 - MA-PD Survey\n47\nVariable\nReverse\n2025\n2024\n2023\n2022\n2021\n2020\n2019\n2018\n2017\nYear 19\nYear 18\nYear 17\nYear 16\nYear 15\nYear 14\nYear 13\nYear 12\nYear 11\nagecat\nsex\neduc\nQ59\nQ62\nQ61\nQ61\nQ61\nQ61\nQ61\nQ61\nrace_hisp\nQ60\nQ63\nQ62\nQ62\nQ62\nQ62\nQ62\nQ62\nrace_white\nQ61E\nQ64E\nQ63E\nQ63A\nQ63A\nQ63A\nQ63A\nQ63A\nrace_black\nQ61C\nQ64C\nQ63C\nQ63B\nQ63B\nQ63B\nQ63B\nQ63B\nrace_asian\nQ61B\nQ64B\nQ63B\nQ63C\nQ63C\nQ63C\nQ63C\nQ63C\nrace_paciﬁc\nQ61D\nQ64D\nQ63D\nQ63D\nQ63D\nQ63D\nQ63D\nQ63D\nrace_natamer\nQ61A\nQ64A\nQ63",
  "dataset": "cahps",
  "url": "https://resdac.org/sites/datadocumentation.resdac.org/files/2026-05/MA_PDP_CAHPS_DataDictionary_2025_CCW.pdf"
}