{
  "chunk_id": "max-ip__data-documentation__515e0f4b8a__chunk_1",
  "source_document": "data/raw/html/documentation_page/515e0f4b8a82429031028f6befb46024fb536839.html",
  "page": null,
  "text": "| Race - Am Indian/Alaskan (from MSIS) | \n\n | RACE_CODE_4 | Race - Asian (from MSIS) | \n\n | RACE_CODE_5 | Race - Hawaiian/Pac Islands (from MSIS) | \n\n | ETHNICITY_CODE | Ethnicity - Hispanic (from MSIS) | \n\n | EL_SS_ELGBLTY_CD_LTST | State specific eligibility - most recent | \n\n | EL_SS_ELGBLTY_CD_MO | State specific eligibility - mo of svc | \n\n | EL_MAX_ELGBLTY_CD_LTST | MAX eligibility - most recent | \n\n | EL_MAX_ELGBLTY_CD_MO | MAX eligibility - mo of svc | \n\n | EL_MDCR_ANN_XOVR_OLD |",
  "dataset": "max-ip",
  "url": "https://resdac.org/cms-data/files/max-ip/data-documentation"
}