{
  "chunk_id": "mbsf-30-cc__ccw-condition-categories-impact-of-transition-from-27-to-30_pdf__397fc86416__p19__chunk_3",
  "source_document": "data/raw/assets/pdf/397fc86416f84595f04fdcac403dfce16ac06e4d.pdf",
  "page": 19,
  "text": "Heart Disease \n4,341,447 \n4,023,300 \n92.7% \n278,673 \n6.4% \n39,474 \n0.9% \nHip/Pelvic Fracture \n505,155 \n116,731 \n23.1% \n21,335 \n4.2% \n367,089 \n72.7% \nHyperlipidemia \n21,899,277 \n18,047,893 \n82.4% \n3,613,039 \n16.5% \n238,345 \n1.1% \nHypertension \n25,041,546 \n20,825,235 \n83.2% \n4,111,919 \n16.4% \n104,392 \n0.4% \nHypothyroidism \n7,336,251 \n5,737,521 \n78.2% \n1,535,919 \n20.9% \n62,811 \n0.9% \nIschemic Heart Disease \n7,902,514 \n7,602,814 \n96.2% \n299,700 \n3.8% \n0 \n0.0% \nNon-Alzheimer's \nDementia \n2,917,887",
  "dataset": "mbsf-30-cc",
  "url": "https://www2.ccwdata.org/documents/10280/19002256/ccw-condition-categories-impact-of-transition-from-27-to-30.pdf"
}