{
  "chunk_id": "medpar__codebook-medpar_pdf__01880a8f13__p258__chunk_0",
  "source_document": "data/raw/assets/pdf/01880a8f130acdc0b26ba14dd05f81632589ce24.pdf",
  "page": 258,
  "text": "Chronic Conditions Warehouse Virtual Research Data Center \nMedPAR Codebook │ April 2025 │ V 4.2 \n\n242 \nUTLZTN_DAY_CNT \nLABEL: \nCovered days of care chargeable to Medicare utilization for stay \nDESCRIPTION: The count of the number of covered days of care that are chargeable to Medicare utilization for the stay. \nSHORT NAME: UTIL_DAY \nLONG NAME: UTLZTN_DAY_CNT \nTYPE: \nNUM \nLENGTH: \n8 \nSOURCE: \nMedPAR (derived) \nVALUES: \n— \nCOMMENT: \nThis field is derived by accumulating the utilization day count",
  "dataset": "medpar",
  "url": "https://www2.ccwdata.org/documents/10280/19022436/Codebook-MedPAR.pdf"
}