{
  "chunk_id": "medpar__codebook-medpar_pdf__01880a8f13__p181__chunk_0",
  "source_document": "data/raw/assets/pdf/01880a8f130acdc0b26ba14dd05f81632589ce24.pdf",
  "page": 181,
  "text": "Chronic Conditions Warehouse Virtual Research Data Center \nMedPAR Codebook │ April 2025 │ V 4.2 \n\n165 \nOXYGN_TAKE_HOME_AMT \nLABEL: \nMedical/Surgical Supplies Oxygen Take Home Amount ($) \nDESCRIPTION: The charge amount (rounded to whole dollars) for the medical/surgical oxygen take home supplies \nrelated to the beneficiary's stay. \nSHORT NAME: OXYGN_TAKE_HOME_AMT \nLONG NAME: OXYGN_TAKE_HOME_AMT \nTYPE: \nNUM \nLENGTH: \n8 \nSOURCE: \nMedPAR (derived) \nVALUES: \n— \nCOMMENT: \nThis field is derived by",
  "dataset": "medpar",
  "url": "https://www2.ccwdata.org/documents/10280/19022436/Codebook-MedPAR.pdf"
}