{
  "chunk_id": "medpar__codebook-medpar_pdf__01880a8f13__p106__chunk_0",
  "source_document": "data/raw/assets/pdf/01880a8f130acdc0b26ba14dd05f81632589ce24.pdf",
  "page": 106,
  "text": "Chronic Conditions Warehouse Virtual Research Data Center \nMedPAR Codebook │ April 2025 │ V 4.2 \n\n90 \nESRD_COND_CD \nLABEL: \nEnd Stage Renal Disease (ESRD) Condition Indicator Code \nDESCRIPTION: The code indicating if the beneficiary had an end stage renal disease (ESRD) condition reported during \nthe stay. \nSHORT NAME: ESRD_CD \nLONG NAME: ESRD_COND_CD \nTYPE: \nCHAR \nLENGTH: \n2 \nSOURCE: \nMedPAR (derived) \nVALUES: \n00 = No dialysis or ESRD services \n71 = Billing is for a patient who received staff",
  "dataset": "medpar",
  "url": "https://www2.ccwdata.org/documents/10280/19022436/Codebook-MedPAR.pdf"
}