{
  "chunk_id": "ocm-current-clinical-status__codebook-ocm_pdf__687e14bf31__p26__chunk_0",
  "source_document": "data/raw/assets/pdf/687e14bf310457071225d4833378b7f8cecd7290.pdf",
  "page": 26,
  "text": "Chronic Conditions Warehouse Virtual Research Data Center \nCODEBOOK: Medicare Oncology Care Model Files │ May 2024 │ V 1.0 \n22 \nPRMRY_TUMOR \nLABEL: \nPrimary Tumor Staging \nDESCRIPTION: Primary tumor staging. \nSHORT NAME: PRMRY_TUMOR \nLONG NAME: PRMRY_TUMOR \nTYPE: \nCHAR \nLENGTH: \n30 \nFILE(S): \nClinical and staging \nSOURCE: \nOncology Care Model Data Registry \nVALUES: \nMultiple Primaries, \nNone Selected, \nT0, \nT1, \nT1a, \nT1a1, \nT1a2, \nT1b, \nT1b1, \nT1b2, \nT1c, \nT1c1, \nT1c2, \nT1c3, \nT1d, \nT1mi, \nT2,",
  "dataset": "ocm-current-clinical-status",
  "url": "https://www2.ccwdata.org/documents/10280/19022436/codebook-ocm.pdf"
}