{
  "chunk_id": "taf-apr__data-documentation__4b6fa6bd99__chunk_15",
  "source_document": "data/raw/html/documentation_page/4b6fa6bd99a6df68962fe05bc883c5d7a0aa4c70.html",
  "page": null,
  "text": "Unit Provider Taxonomy Indicator — Ever in Calendar Year | \n\n | 65 | HOSP_TXNMY_IND | Hospital Provider Taxonomy Indicator — Ever in Calendar Year | \n\n | 66 | LAB_TXNMY_IND | Laboratory Provider Taxonomy Indicator — Ever in Calendar Year | \n\n | 67 | MCO_TXNMY_IND | Managed Care Organization Taxonomy Indicator — Ever in Calendar Year | \n\n | 68 | NRSNG_CSTDL_CARE_PRVDR_TXNMY_IND | Nursing Custodial Care Provider Taxonomy Indicator — Ever in Calendar Year | \n\n | 69 | LDGNG_MEALS_PRVDR_TXNMY_IND |",
  "dataset": "taf-apr",
  "url": "https://resdac.org/cms-data/files/taf-apr/data-documentation"
}